pinject/__init__.py
pinject/annotations.py
pinject/arg_binding_keys.py
pinject/binding_keys.py
pinject/bindings.py
pinject/decorators.py
pinject/errors.py
pinject/finding.py
pinject/initializers.py
pinject/injection_contexts.py
pinject/locations.py
pinject/object_graph.py
pinject/object_providers.py
pinject/provider_indirections.py
pinject/providing.py
pinject/required_bindings.py
pinject/scoping.py
pinject/support.py
pinject/support_test.py
pinject/version.py
pinject-0.14.1.dist-info/METADATA
pinject-0.14.1.dist-info/RECORD
pinject-0.14.1.dist-info/WHEEL
pinject-0.14.1.dist-info/top_level.txt
