Metadata-Version: 1.0
Name: pinject
Version: 0.14.1
Summary: A pythonic dependency injection library
Home-page: https://github.com/google/pinject
Author: Kurt Steinkraus
Author-email: kurt@steinkraus.us
License: Apache License 2.0
Platform: all
